life_restart_core-0.3.3.dist-info/METADATA
life_restart_core-0.3.3.dist-info/WHEEL
life_restart_core/__init__.py
life_restart_core/__init__.pyi
life_restart_core/life_restart_core.cpython-312-aarch64-linux-gnu.so
life_restart_core-0.3.3.dist-info/RECORD
