Metadata-Version: 2.4
Name: life-restart-core
Version: 0.3.3
Classifier: Development Status :: 4 - Beta
Classifier: Intended Audience :: Developers
Classifier: License :: OSI Approved :: MIT License
Classifier: Programming Language :: Python :: 3
Classifier: Programming Language :: Python :: 3.12
Classifier: Programming Language :: Python :: 3.13
Classifier: Programming Language :: Python :: 3.14
Classifier: Programming Language :: Rust
Classifier: Topic :: Games/Entertainment :: Simulation
Summary: High-performance life restart simulator core engine written in Rust
Keywords: game,simulator,rust,performance
License: MIT
Requires-Python: >=3.12
Project-URL: Homepage, https://github.com/qaz17899/life-restart-core
Project-URL: Repository, https://github.com/qaz17899/life-restart-core
Project-URL: Issues, https://github.com/qaz17899/life-restart-core/issues
